{
  "success": true,
  "result": {
    "itunesId": "1624478669",
    "title": "ספריית פיג'מה קוראת לכם!",
    "author": "ספריית פיג׳מה",
    "feedUrl": "https://www.pjisrael.org/feed/podcast/%d7%a1%d7%a4%d7%a8%d7%99%d7%99%d7%aa-%d7%a4%d7%99%d7%92%d7%9e%d7%94-%d7%a7%d7%95%d7%a8%d7%90%d7%aa-%d7%9c%d7%9b%d7%9d/",
    "imageUrl": "https://is1-ssl.mzstatic.com/image/thumb/Podcasts112/v4/81/ec/c6/81ecc6b2-1724-eed0-5fa3-88b410a4311c/mza_5618081949296278396.png/600x600bb.jpg",
    "genre": "Language Learning"
  }
}